<databaseChangeLog xmlns="http://www.liquibase.org/xml/ns/dbchangelog/1.1">
    <changeSet id="1" author="jeffreyh">
        <createTable tableName="user">
            <column name="id" type="int">
                <constraints nullable="true" primaryKey="true" unique="true"/>
            </column>
            <column name="first_name" type="varchar(200)">
                <constraints nullable="true"/>
            </column>
            <column name="last_name" type="varchar(200)">
                <constraints nullable="true"/>
            </column>
        </createTable>
    </changeSet>
</databaseChangeLog>